longsight/__init__.py
longsight/instrumentation.py
longsight-1.0.16.dist-info/licenses/LICENSE.md
longsight-1.0.16.dist-info/METADATA
longsight-1.0.16.dist-info/WHEEL
longsight-1.0.16.dist-info/top_level.txt
longsight-1.0.16.dist-info/RECORD
