Metadata-Version: 2.4
Name: longsight
Version: 1.0.16
Summary: This library implements a range of common logging functions.
Home-page: https://gitlab.com/crossref/labs/distrunner
Author: Martin Paul Eve
Author-email: meve@crossref.org
Maintainer-email: Martin Paul Eve <meve@crossref.org>
License: Copyright &copy; 2023 Crossref
Project-URL: homepage, https://labs.crossref.org
Project-URL: documentation, https://labs.crossref.org
Project-URL: repository, https://gitlab.com/crossref/labs/longsight
Project-URL: changelog, https://gitlab.com/crossref/labs/longsight/-/blob/main/CHANGELOG.md
Keywords: distributed computing
Classifier: Development Status :: 4 - Beta
Classifier: Programming Language :: Python
Requires-Python: >=3.8
License-File: LICENSE.md
Requires-Dist: aws-lambda-powertools[all]==2.11.0
Requires-Dist: fastapi~=0.95.0
Requires-Dist: starlette==0.26.1
Requires-Dist: claws>=0.0.20
Requires-Dist: watchtower==3.0.1
Dynamic: license-file
